[
    {
        "datetime_utc": 1747636412323,
        "predicted": true
    },
    {
        "datetime_utc": 1747911912946,
        "predicted": true
    },
    {
        "datetime_utc": 1748187384145,
        "predicted": true
    },
    {
        "datetime_utc": 1748462856515,
        "predicted": true
    },
    {
        "datetime_utc": 1748738328838,
        "predicted": true
    },
    {
        "datetime_utc": 1749013801164,
        "predicted": true
    },
    {
        "datetime_utc": 1749289273489,
        "predicted": true
    },
    {
        "datetime_utc": 1749564745814,
        "predicted": true
    },
    {
        "datetime_utc": 1749840218139,
        "predicted": true
    },
    {
        "datetime_utc": 1750115690464,
        "predicted": true
    }
]