[
    {
        "datetime_utc": 1750698761938,
        "predicted": true
    },
    {
        "datetime_utc": 1750974567157,
        "predicted": true
    },
    {
        "datetime_utc": 1751250385771,
        "predicted": true
    },
    {
        "datetime_utc": 1751526204889,
        "predicted": true
    },
    {
        "datetime_utc": 1751802024026,
        "predicted": true
    },
    {
        "datetime_utc": 1752077843164,
        "predicted": true
    },
    {
        "datetime_utc": 1752353662302,
        "predicted": true
    },
    {
        "datetime_utc": 1752629481439,
        "predicted": true
    },
    {
        "datetime_utc": 1752905300577,
        "predicted": true
    },
    {
        "datetime_utc": 1753181119715,
        "predicted": true
    }
]