[
    {
        "datetime_utc": 1747080370990,
        "predicted": true
    },
    {
        "datetime_utc": 1747355771749,
        "predicted": true
    },
    {
        "datetime_utc": 1747631177243,
        "predicted": true
    },
    {
        "datetime_utc": 1747906582616,
        "predicted": true
    },
    {
        "datetime_utc": 1748181987991,
        "predicted": true
    },
    {
        "datetime_utc": 1748457393367,
        "predicted": true
    },
    {
        "datetime_utc": 1748732798742,
        "predicted": true
    },
    {
        "datetime_utc": 1749008204118,
        "predicted": true
    },
    {
        "datetime_utc": 1749283609494,
        "predicted": true
    },
    {
        "datetime_utc": 1749559014869,
        "predicted": true
    }
]