[
    {
        "datetime_utc": 1757819199804,
        "predicted": true
    },
    {
        "datetime_utc": 1758094585254,
        "predicted": true
    },
    {
        "datetime_utc": 1758369970837,
        "predicted": true
    },
    {
        "datetime_utc": 1758645356423,
        "predicted": true
    },
    {
        "datetime_utc": 1758920742010,
        "predicted": true
    },
    {
        "datetime_utc": 1759196127596,
        "predicted": true
    },
    {
        "datetime_utc": 1759471513182,
        "predicted": true
    },
    {
        "datetime_utc": 1759746898769,
        "predicted": true
    },
    {
        "datetime_utc": 1760022284355,
        "predicted": true
    },
    {
        "datetime_utc": 1760297669941,
        "predicted": true
    }
]