{
    "current": {
        "datetime_utc": 1751530298363,
        "predicted": true
    },
    "predicted": [
        {
            "datetime_utc": 1751806154606,
            "predicted": true
        },
        {
            "datetime_utc": 1752082018112,
            "predicted": true
        },
        {
            "datetime_utc": 1752357881795,
            "predicted": true
        },
        {
            "datetime_utc": 1752633745483,
            "predicted": true
        },
        {
            "datetime_utc": 1752909609171,
            "predicted": true
        }
    ]
}